AUTHORS
CHANGES
LICENSE
MANIFEST.in
Makefile
README.md
pynag.spec
setup.py
debian.upstream/changelog
debian.upstream/compat
debian.upstream/control
debian.upstream/copyright
debian.upstream/rules
debian.upstream/watch
debian.upstream/source/format
docs/Makefile
docs/conf.py
docs/index.rst
docs/introduction.rst
docs/make.bat
docs/modules.rst
docs/pynag-command.rst
docs/pynag.Control.Command.rst
docs/pynag.Control.rst
docs/pynag.Model.EventHandlers.rst
docs/pynag.Model.rst
docs/pynag.Parsers.rst
docs/pynag.Plugins.rst
docs/pynag.Utils.rst
docs/pynag.rst
docs/_static/ajax-loader.gif
docs/_static/basic.css
docs/_static/comment-bright.png
docs/_static/comment-close.png
docs/_static/comment.png
docs/_static/default.css
docs/_static/doctools.js
docs/_static/down-pressed.png
docs/_static/down.png
docs/_static/file.png
docs/_static/jquery.js
docs/_static/minus.png
docs/_static/plus.png
docs/_static/pygments.css
docs/_static/searchtools.js
docs/_static/sidebar.js
docs/_static/underscore.js
docs/_static/up-pressed.png
docs/_static/up.png
docs/_static/websupport.js
examples/README
examples/Model/edit_service.py
examples/Model/list_all_hostgroups.py
examples/Model/list_all_services.py
examples/Model/list_services_for_one_host.py
examples/Model/parse-configmain.py
examples/Model/remove_empty_configfiles.py
examples/Model/restructure_config_files.py
examples/Model/working_with_fields.py
examples/Parsers/find_orphans.py
examples/Parsers/get_command.py
examples/Parsers/get_contact.py
examples/Parsers/get_contactgroup.py
examples/Parsers/get_host.py
examples/Parsers/get_hostgroup.py
examples/Parsers/get_service.py
examples/Parsers/get_service_info.py
examples/Parsers/get_servicegroup.py
examples/Parsers/get_timeperiod.py
examples/Parsers/list_hosts_groups.py
examples/Parsers/list_services.py
examples/Parsers/optimize_config.py
examples/Parsers/parse_files.py
examples/Parsers/remove_host.py
examples/Parsers/remove_host_from_group.py
examples/Parsers/suggest_optimizations.py
pynag.egg-info/PKG-INFO
pynag.egg-info/SOURCES.txt
pynag.egg-info/dependency_links.txt
pynag.egg-info/requires.txt
pynag.egg-info/top_level.txt
