Metadata-Version: 1.1
Name: pynag
Version: 1.1.2
Summary: Python modules for Nagios plugins and configuration
Home-page: http://pynag.org/
Author: Drew Stinnett
Author-email: drew@drewlink.com
License: GPLv2
Platform: UNKNOWN
Requires: unittest2
